setup.cfg
setup.py
qmc5883l/__init__.py
qmc5883l.egg-info/PKG-INFO
qmc5883l.egg-info/SOURCES.txt
qmc5883l.egg-info/dependency_links.txt
qmc5883l.egg-info/not-zip-safe
qmc5883l.egg-info/top_level.txt