Metadata-Version: 1.1
Name: qmc5883l
Version: 0.92
Summary: Driver for qmc5883l 3-Axis Magnetic Sensor
Home-page: http://github.com/norges/qmc5883l
Author: Fabian Mruck
Author-email: github@ffabi.com
License: MIT
Download-URL: http://github.com/norges/qmc5883l/archive/0.92.tar.gz)
Platform: UNKNOWN
